torchcfm/__init__.py
torchcfm/conditional_flow_matching.py
torchcfm/optimal_transport.py
torchcfm/utils.py
torchcfm/version.py
torchcfm/models/__init__.py
torchcfm/models/models.py
torchcfm/models/unet/__init__.py
torchcfm/models/unet/fp16_util.py
torchcfm/models/unet/logger.py
torchcfm/models/unet/nn.py
torchcfm/models/unet/unet.py
torchcfm-1.0.7.dist-info/LICENSE
torchcfm-1.0.7.dist-info/METADATA
torchcfm-1.0.7.dist-info/WHEEL
torchcfm-1.0.7.dist-info/top_level.txt
torchcfm-1.0.7.dist-info/RECORD
