Metadata-Version: 2.2
Name: torchcfm
Version: 1.0.7
Summary: Conditional Flow Matching for Fast Continuous Normalizing Flow Training.
Home-page: https://github.com/atong01/conditional-flow-matching
Author: Alexander Tong, Kilian Fatras
Author-email: alexandertongdev@gmail.com
License: MIT
License-File: LICENSE
Requires-Dist: torch>=1.11.0
Requires-Dist: matplotlib
Requires-Dist: numpy
Requires-Dist: scipy
Requires-Dist: scikit-learn
Requires-Dist: torchdyn>=1.0.6
Requires-Dist: pot
Requires-Dist: torchdiffeq
Requires-Dist: absl-py
Requires-Dist: pandas>=2.2.2
Provides-Extra: forest-flow
Requires-Dist: xgboost; extra == "forest-flow"
Requires-Dist: scikit-learn; extra == "forest-flow"
Requires-Dist: ForestDiffusion; extra == "forest-flow"
Dynamic: author
Dynamic: author-email
Dynamic: description
Dynamic: description-content-type
Dynamic: home-page
Dynamic: license
Dynamic: provides-extra
Dynamic: requires-dist
Dynamic: summary
